bitlinear_pytorch/__init__.py
bitlinear_pytorch/bitlinear.py
bitlinear_pytorch-0.5.0.dist-info/LICENSE
bitlinear_pytorch-0.5.0.dist-info/METADATA
bitlinear_pytorch-0.5.0.dist-info/WHEEL
bitlinear_pytorch-0.5.0.dist-info/top_level.txt
bitlinear_pytorch-0.5.0.dist-info/RECORD
