Metadata-Version: 2.1
Name: bitlinear-pytorch
Version: 0.5.0
Summary: Implementation of the BitLinear layer from: The Era of 1-bit LLMs: All Large Language Models are in 1.58 Bits
Author-email: Ingur Veken <ingurv99@gmail.com>, Niels Rouws <nrouws@gmail.com>
License: MIT License
Project-URL: Homepage, https://github.com/ingur/bitlinear-pytorch
Project-URL: Issues, https://github.com/ingur/bitlinear-pytorch/issues
Keywords: pytorch,bitlinear,bitnet,quantization,linear,layer,ternary,binary,quantized,quantized weights
Classifier: Development Status :: 3 - Alpha
Classifier: Intended Audience :: Developers
Classifier: Topic :: Scientific/Engineering :: Artificial Intelligence
Classifier: License :: OSI Approved :: MIT License
License-File: LICENSE
Requires-Dist: torch>=1.10.0
Provides-Extra: test
Requires-Dist: pytest; extra == "test"
Requires-Dist: pytest-runner; extra == "test"
